[
  {
    "id": 1,
    "title": "Gemüse-Lasagne",
    "description": "Schichten aus Pasta mit Spinat, Ricotta und Tomatensauce.",
    "season": "Winter",
    "ingredients": [
      { "name": "Lasagne-Nudeln", "amount": "250g" },
      { "name": "Ricotta", "amount": "200g" },
      { "name": "Spinat", "amount": "200g" },
      { "name": "Tomatensauce", "amount": "500ml" },
      { "name": "Mozzarella", "amount": "200g, gerieben" },
      { "name": "Knoblauch", "amount": "2 Zehen, gehackt" },
      { "name": "Olivenöl", "amount": "1 EL" },
      { "name": "Salz", "amount": "nach Geschmack" },
      { "name": "Schwarzer Pfeffer", "amount": "nach Geschmack" }
    ]
  },
  {
    "id": 2,
    "title": "Caprese-Salat",
    "description": "Tomaten, Mozzarella und Basilikum mit Olivenöl beträufelt.",
    "season": "Summer",
    "ingredients": [
      { "name": "Tomaten", "amount": "3 große, in Scheiben" },
      { "name": "Mozzarella", "amount": "200g" },
      { "name": "Basilikumblätter", "amount": "eine Handvoll" },
      { "name": "Olivenöl", "amount": "2 EL" },
      { "name": "Balsamico-Essig", "amount": "1 EL" },
      { "name": "Salz", "amount": "nach Geschmack" },
      { "name": "Schwarzer Pfeffer", "amount": "nach Geschmack" }
    ]
  },
  {
    "id": 3,
    "title": "Gegrillte Gemüsespieße",
    "description": "Buntes Gemüse auf Spießen mit einer leichten Marinade gegrillt.",
    "season": "Summer",
    "ingredients": [
      { "name": "Zucchini", "amount": "1, in Scheiben" },
      { "name": "Paprika", "amount": "2, gewürfelt" },
      { "name": "Champignons", "amount": "200g" },
      { "name": "Cherrytomaten", "amount": "150g" },
      { "name": "Olivenöl", "amount": "2 EL" },
      { "name": "Sojasauce", "amount": "1 EL" },
      { "name": "Knoblauch", "amount": "2 Zehen, gehackt" },
      { "name": "Salz", "amount": "nach Geschmack" },
      { "name": "Schwarzer Pfeffer", "amount": "nach Geschmack" }
    ]
  },
  {
    "id": 4,
    "title": "Linsensuppe",
    "description": "Herzhafte Suppe mit Linsen und Gemüse.",
    "season": "Winter",
    "ingredients": [
      { "name": "Linsen", "amount": "200g" },
      { "name": "Karotten", "amount": "2, gehackt" },
      { "name": "Sellerie", "amount": "2 Stangen, gehackt" },
      { "name": "Zwiebel", "amount": "1, gehackt" },
      { "name": "Gemüsebrühe", "amount": "1 Liter" },
      { "name": "Tomatenmark", "amount": "2 EL" },
      { "name": "Olivenöl", "amount": "1 EL" },
      { "name": "Kreuzkümmel", "amount": "1 TL" },
      { "name": "Salz", "amount": "nach Geschmack" },
      { "name": "Schwarzer Pfeffer", "amount": "nach Geschmack" }
    ]
  },
  {
    "id": 5,
    "title": "Gemüsepfanne",
    "description": "Schnelle und gesunde Pfanne mit gemischtem Gemüse und Sojasauce.",
    "season": "Spring",
    "ingredients": [
      { "name": "Brokkoli", "amount": "200g, Röschen" },
      { "name": "Karotten", "amount": "2, in Streifen" },
      { "name": "Paprika", "amount": "2, in Scheiben" },
      { "name": "Zwiebel", "amount": "1 mittelgroß, in Scheiben" },
      { "name": "Sojasauce", "amount": "2 EL" },
      { "name": "Sesamöl", "amount": "1 EL" },
      { "name": "Knoblauch", "amount": "2 Zehen, gehackt" },
      { "name": "Ingwer", "amount": "1 Stück, gehackt" },
      { "name": "Salz", "amount": "nach Geschmack" },
      { "name": "Schwarzer Pfeffer", "amount": "nach Geschmack" }
    ]
  },
  {
    "id": 6,
    "title": "Kürbissuppe",
    "description": "Cremige Suppe aus geröstetem Kürbis und Gewürzen.",
    "season": "Fall",
    "ingredients": [
      { "name": "Kürbis", "amount": "500g, gewürfelt" },
      { "name": "Zwiebel", "amount": "1 groß, gehackt" },
      { "name": "Knoblauch", "amount": "2 Zehen, gehackt" },
      { "name": "Gemüsebrühe", "amount": "750ml" },
      { "name": "Kokosmilch", "amount": "200ml" },
      { "name": "Olivenöl", "amount": "1 EL" },
      { "name": "Muskat", "amount": "1/4 TL" },
      { "name": "Salz", "amount": "nach Geschmack" },
      { "name": "Schwarzer Pfeffer", "amount": "nach Geschmack" }
    ]
  },
  {
    "id": 7,
    "title": "Kichererbsen-Tacos",
    "description": "Weiche Tortillas gefüllt mit gewürzten Kichererbsen und Belag.",
    "season": "Summer",
    "ingredients": [
      { "name": "Kichererbsen", "amount": "400g, gekocht" },
      { "name": "Taco-Gewürz", "amount": "2 EL" },
      { "name": "weiche Tortillas", "amount": "8" },
      { "name": "Salsa", "amount": "1/2 Tasse" },
      { "name": "Avocado", "amount": "1, in Scheiben" },
      { "name": "Kopfsalat", "amount": "1/2 Kopf, geschnitten" },
      { "name": "Koriander", "amount": "1/4 Tasse, gehackt" }
    ]
  },
  {
    "id": 8,
    "title": "Auberginen-Parmesan",
    "description": "Frittierte Auberginenscheiben mit Marinara-Sauce und geschmolzenem Käse.",
    "season": "Fall",
    "ingredients": [
      { "name": "Aubergine", "amount": "2 mittelgroß, in Scheiben" },
      { "name": "Paniermehl", "amount": "1 Tasse" },
      { "name": "Ei", "amount": "1, verquirlt" },
      { "name": "Marinara-Sauce", "amount": "1 Tasse" },
      { "name": "Mozzarella", "amount": "200g, gerieben" },
      { "name": "Parmesan", "amount": "50g, gerieben" },
      { "name": "Olivenöl", "amount": "zum Frittieren" },
      { "name": "Salz", "amount": "nach Geschmack" },
      { "name": "Schwarzer Pfeffer", "amount": "nach Geschmack" }
    ]
  },
  {
    "id": 9,
    "title": "Caesar-Salat",
    "description": "Klassischer Caesar-Salat mit Römersalat, Croutons und cremigem Dressing.",
    "season": "Summer",
    "ingredients": [
      { "name": "Römersalat", "amount": "2 Köpfe, gehackt" },
      { "name": "Croutons", "amount": "1 Tasse" },
      { "name": "Parmesan", "amount": "50g, gerieben" },
      { "name": "Caesar-Dressing", "amount": "1/2 Tasse" },
      { "name": "Salz", "amount": "nach Geschmack" },
      { "name": "Schwarzer Pfeffer", "amount": "nach Geschmack" }
    ]
  },
  {
    "id": 10,
    "title": "Gefüllte Paprika",
    "description": "Paprika gefüllt mit Reis, Bohnen und Käse.",
    "season": "Spring",
    "ingredients": [
      { "name": "Paprika", "amount": "4, halbiert" },
      { "name": "gekochter Reis", "amount": "1 Tasse" },
      { "name": "schwarze Bohnen", "amount": "1 Tasse" },
      { "name": "Mais", "amount": "1/2 Tasse" },
      { "name": "Tomatensauce", "amount": "1 Tasse" },
      { "name": "Käse", "amount": "1/2 Tasse, gerieben" },
      { "name": "Zwiebel", "amount": "1, gehackt" },
      { "name": "Knoblauch", "amount": "2 Zehen, gehackt" },
      { "name": "Olivenöl", "amount": "1 EL" },
      { "name": "Salz", "amount": "nach Geschmack" },
      { "name": "Schwarzer Pfeffer", "amount": "nach Geschmack" }
    ]
  },
  {
    "id": 11,
    "title": "Pilzrisotto",
    "description": "Cremiges Risotto mit sautierten Pilzen und Parmesan.",
    "season": "Fall",
    "ingredients": [
      { "name": "Arborio-Reis", "amount": "200g" },
      { "name": "Champignons", "amount": "200g, in Scheiben" },
      { "name": "Zwiebel", "amount": "1 klein, gehackt" },
      { "name": "Knoblauch", "amount": "2 Zehen, gehackt" },
      { "name": "Gemüsebrühe", "amount": "750ml" },
      { "name": "Weißwein", "amount": "100ml" },
      { "name": "Parmesan", "amount": "50g, gerieben" },
      { "name": "Butter", "amount": "2 EL" },
      { "name": "Olivenöl", "amount": "1 EL" },
      { "name": "Salz", "amount": "nach Geschmack" },
      { "name": "Schwarzer Pfeffer", "amount": "nach Geschmack" }
    ]
  }
]
